mozichem_ai/__init__.py
mozichem_ai/app.py
mozichem_ai/agents/__init__.py
mozichem_ai/agents/main.py
mozichem_ai/agents/mcp_manager.py
mozichem_ai/agents/mozichem_agent.py
mozichem_ai/api/__init__.py
mozichem_ai/api/ai_api.py
mozichem_ai/api/config_api.py
mozichem_ai/api/llm.py
mozichem_ai/api/main.py
mozichem_ai/config/__init__.py
mozichem_ai/config/constants.py
mozichem_ai/config/settings.py
mozichem_ai/docs/__init__.py
mozichem_ai/docs/core.py
mozichem_ai/errors/__init__.py
mozichem_ai/llms/__init__.py
mozichem_ai/llms/llm_models.py
mozichem_ai/memory/__init__.py
mozichem_ai/memory/config_memory.py
mozichem_ai/models/__init__.py
mozichem_ai/models/api.py
mozichem_ai/models/chat.py
mozichem_ai/models/llm.py
mozichem_ai/models/mcp.py
mozichem_ai/ui/3rdpartylicenses.txt
mozichem_ai/ui/prerendered-routes.json
mozichem_ai/ui/browser/favicon.ico
mozichem_ai/ui/browser/index.html
mozichem_ai/ui/browser/main-P4CXXPNI.js
mozichem_ai/ui/browser/mozichem.ico
mozichem_ai/ui/browser/styles-VKLEA4UG.css
mozichem_ai/ui/browser/assets/image/mozichem.png
mozichem_ai/utils/__init__.py
mozichem_ai/utils/loader.py
mozichem_ai/utils/message_manager.py
mozichem_ai-0.1.1.dist-info/licenses/LICENSE
mozichem_ai-0.1.1.dist-info/METADATA
mozichem_ai-0.1.1.dist-info/WHEEL
mozichem_ai-0.1.1.dist-info/top_level.txt
mozichem_ai-0.1.1.dist-info/RECORD
